{
  "mesopotamia": {
    "titulo": "Mesopotâmia",
    "perguntas": [

      {
        "pergunta": "O termo Mesopotâmia foi criado por autores gregos muito tempo depois do florescimento dessas civilizações. Qual é o significado literal da palavra Mesopotâmia?",
        "opcoes": [
          "Terra fértil",
          "Terra entre rios",
          "Terra dos deuses",
          "Terra das cidades"
        ],
        "correta": 1
      },

      {
        "pergunta": "A expressão Mesopotâmia faz referência direta a dois grandes rios que estruturaram a vida econômica e social da região. Quais eram esses rios?",
        "opcoes": [
          "Nilo e Jordão",
          "Tigre e Eufrates",
          "Indo e Ganges",
          "Danúbio e Reno"
        ],
        "correta": 1
      },

      {
        "pergunta": "A maior parte do território da antiga Mesopotâmia corresponde, hoje, principalmente a qual país moderno?",
        "opcoes": [
          "Síria",
          "Irã",
          "Iraque",
          "Turquia"
        ],
        "correta": 2
      },

      {
        "pergunta": "As principais construções religiosas das cidades mesopotâmicas tinham formato de pirâmide escalonada e funcionavam como centros de culto e administração. Como essas construções eram chamadas?",
        "opcoes": [
          "Pirâmides",
          "Zigurates",
          "Obeliscos",
          "Templos subterrâneos"
        ],
        "correta": 1
      },

      {
        "pergunta": "Na Mesopotâmia surgiu o sistema de escrita mais antigo conhecido da história humana, desenvolvido inicialmente para atender necessidades práticas das cidades. Qual é o nome dessa escrita?",
        "opcoes": [
          "Hieroglífica",
          "Cuneiforme",
          "Alfabética",
          "Linear"
        ],
        "correta": 1
      },

      {
        "pergunta": "A escrita cuneiforme era registrada por meio de marcas em forma de cunha feitas em um material abundante na região. Em qual material esses textos eram gravados?",
        "opcoes": [
          "Papiro",
          "Pergaminho",
          "Tábuas de argila",
          "Placas de madeira"
        ],
        "correta": 2
      },

      {
        "pergunta": "Quando surgiu, a escrita cuneiforme não tinha finalidade literária ou religiosa. Qual era seu principal uso inicial?",
        "opcoes": [
          "Registro de mitos",
          "Controle administrativo e contábil",
          "Ensino religioso",
          "Correspondência pessoal"
        ],
        "correta": 1
      },

      {
        "pergunta": "A obra literária mais antiga conhecida da história humana foi registrada na Mesopotâmia e narra as aventuras de um rei lendário. Qual é o nome dessa obra?",
        "opcoes": [
          "Código de Hamurábi",
          "Epopeia de Gilgámesh",
          "Livro dos Mortos",
          "Ilíada"
        ],
        "correta": 1
      },

      {
        "pergunta": "A Epopeia de Gilgámesh trata principalmente de uma questão central da condição humana, explorada a partir da amizade, da morte e da jornada do herói. Qual é o tema central dessa narrativa?",
        "opcoes": [
          "Expansão territorial",
          "Busca pela imortalidade",
          "Origem dos deuses",
          "Fundação das cidades"
        ],
        "correta": 1
      },

      {
        "pergunta": "Na Mesopotâmia viveu a primeira autora conhecida da história a assinar seus próprios textos. Filha do rei acádio Sargão, ela foi alta sacerdotisa, escreveu hinos religiosos em primeira pessoa e teve seu nome preservado. Quem foi essa autora?",
        "opcoes": [
          "Ishtar",
          "Enheduana",
          "Ninsun",
          "Semíramis"
        ],
        "correta": 1
      },

      {
        "pergunta": "Quem foram os fundadores das primeiras cidades na Mesopotâmia, como Ur e Uruk?",
        "opcoes": [
          "Acádios",
          "Sumérios",
          "Babilônios",
          "Assírios"
        ],
        "correta": 1
      },
      
      {
        "pergunta": "Os primeiros povos responsáveis pela fundação das cidades mesopotâmicas foram os sumérios, estabelecidos principalmente no sul da região. Como se organizavam politicamente essas cidades?",
        "opcoes": [
          "Império unificado",
          "Cidades-estado independentes",
          "Confederação tribal",
          "Monarquia feudal"
        ],
        "correta": 1
      },

      {
        "pergunta": "Além da escrita cuneiforme, os sumérios desenvolveram outras inovações fundamentais para a história humana. Qual dessas é corretamente atribuída a eles e está presente em nossa forma de marcar o tempo até os dias de hoje?",
        "opcoes": [
          "Sistema sexagesimal (base 60)",
          "Alfabeto fonético",
          "Calendário solar anual",
          "Democracia representativa"
        ],
        "correta": 0
      },

      {
        "pergunta": "Qual civilização mesopotâmica formou um dos primeiros impérios territoriais da história?",
        "opcoes": [
          "Assírios",
          "Acádios",
          "Caldeus",
          "Hititas"
        ],
        "correta": 1
      },
      {
        "pergunta": "O principal governante do Império Acádio foi Sargão, responsável por uma transformação política inédita na região. Qual foi sua principal realização?",
        "opcoes": [
          "Criar cidades-estado independentes",
          "Unificar várias cidades sob um único poder imperial",
          "Estabelecer o primeiro código de leis",
          "Fundar a cidade da Babilônia"
        ],
        "correta": 1
      },
      {
        "pergunta": "Durante o Império Acádio, ocorreu uma mudança importante na cultura escrita mesopotâmica. Qual foi a principal inovação introduzida pelos acádios nesse campo?",
        "opcoes": [
          "Criação de um novo sistema de escrita",
          "Uso de uma língua semítica na escrita cuneiforme",
          "Substituição da escrita por registros orais",
          "Abandono do sumério como língua culta"
        ],
        "correta": 1
      },
      {
        "pergunta": "Após o declínio do Império Acádio, um povo de origem amorita estabeleceu um novo reino na Mesopotâmia central. Qual cidade tornou-se o principal centro político desse reino?",
        "opcoes": [
          "Ur",
          "Lagash",
          "Babilônia",
          "Nínive"
        ],
        "correta": 2
      },
      {
        "pergunta": "O rei mais conhecido da Babilônia Antiga foi Hamurábi. Por qual motivo histórico ele é lembrado?",
        "opcoes": [
          "Conquistas marítimas",
          "Elaboração de um código de leis escrito",
          "Criação do alfabeto",
          "Reforma religiosa monoteísta"
        ],
        "correta": 1
      },
      {
        "pergunta": "O Código de Hamurábi estabelecia punições diferentes conforme a posição social das pessoas envolvidas. Como é conhecido esse princípio jurídico?",
        "opcoes": [
          "Direito natural",
          "Lei de talião",
          "Justiça universal",
          "Direito consuetudinário"
        ],
        "correta": 1
      },
      {
        "pergunta": "No norte da Mesopotâmia, os assírios construíram um império marcado pela expansão territorial. Qual característica foi central para o poder assírio?",
        "opcoes": [
          "Pacifismo religioso",
          "Militarismo intenso",
          "Economia baseada no comércio marítimo",
          "Isolamento cultural"
        ],
        "correta": 1
      },
      {
        "pergunta": "Durante o auge do Império Assírio, uma cidade tornou-se seu principal centro político e administrativo e também abrigou a sede da lendária Biblioteca de Assurbanípal, uma coleção de milhares de placas de argila contendo escritos em cuneiforme. Qual era essa cidade?",
        "opcoes": [
          "Uruk",
          "Babilônia",
          "Nínive",
          "Eridu"
        ],
        "correta": 2
      },
      {
        "pergunta": "Os assírios utilizavam deportações em massa como estratégia de dominação imperial. Qual era o principal objetivo dessa prática?",
        "opcoes": [
          "Gerar mais empregos a cidadãos assírios",
          "Evitar revoltas e resistências locais",
          "Promover integração cultural voluntária",
          "Expandir a produção agrícola"
        ],
        "correta": 1
      },
      {
        "pergunta": "Após a queda do Império Assírio, qual povo assumiu a região criando o Império Neobabilônico?",
        "opcoes": [
          "Sumérios",
          "Caldeus",
          "Acádios",
          "Elamitas"
        ],
        "correta": 2
      },
      {
        "pergunta": "O governante mais associado ao auge do Império Neobabilônico foi Nabucodonosor II. Qual realização marcou seu governo?",
        "opcoes": [
          "Fundação do Império Acádio",
          "Reconstrução monumental da Babilônia",
          "Criação do alfabeto fonético",
          "Conversão oficial ao monoteísmo"
        ],
        "correta": 1
      },

      {
        "pergunta": "Quais construções lendárias são associadas a Nabucodonosor II?",
        "opcoes": [
          "Vale dos Reis e Pirâmides de Gizé",
          "Jardins Suspensos da Babilônia e Torre de Babel",
          "Jardins Suspensos da Babilônia e Vale dos Reis",
          "Torre de Babel e Satrapas de Ciro"
        ],
        "correta": 1
      },
      
      {
  "pergunta": "Como era chamado o governante-rei de uma cidade-estado mesopotâmica?",
  "opcoes": [
    "Faraó",
    "Lugal",
    "Basileu",
    "Cônsul"
  ],
  "correta": 1
},
{
  "pergunta": "Qual título era dado ao governante-sacerdote nas cidades mesopotâmicas?",
  "opcoes": [
    "Vizir",
    "Patesi",
    "Sumo sacerdote",
    "Nômade"
  ],
  "correta": 1
},
{
  "pergunta": "Qual deus sumério era associado ao céu e à autoridade suprema?",
  "opcoes": [
    "Enki",
    "Anu",
    "Ishtar",
    "Nergal"
  ],
  "correta": 1
},
{
  "pergunta": "Qual divindade mesopotâmica estava ligada à sabedoria, à água doce e à criação?",
  "opcoes": [
    "Enlil",
    "Shamash",
    "Enki",
    "Marduk"
  ],
  "correta": 2
},
{
  "pergunta": "Qual deusa mesopotâmica era associada ao amor, à fertilidade e à guerra?",
  "opcoes": [
    "Ereshkigal",
    "Ishtar",
    "Ninsun",
    "Tiamat"
  ],
  "correta": 1
},
{
  "pergunta": "Qual deus tornou-se o principal da Babilônia, especialmente durante o reinado de Hamurábi?",
  "opcoes": [
    "Anu",
    "Enlil",
    "Marduk",
    "Shamash"
  ],
  "correta": 2
},
      
      {
        "pergunta": "A autonomia política da Mesopotâmia chegou ao fim no século VI a.C., quando a região foi conquistada por um grande império estrangeiro. Qual foi esse império?",
        "opcoes": [
          "Egípcio",
          "Grego",
          "Persa",
          "Romano"
        ],
        "correta": 2
      }
      

    ]
  }

{
  "hebreus": {
    "titulo": "Hebreus",
    "perguntas": [
      {
        "pergunta": "1) A fase mais antiga da história hebraica, marcada por Abraão, Isaac e Jacó, é conhecida como:",
        "opcoes": [
          "Período dos Juízes",
          "Era dos Patriarcas",
          "Período Helenístico",
          "Período Romano"
        ],
        "correta": 1
      },
      {
        "pergunta": "2) Segundo a tradição, Abraão sai de Ur e migra para Canaã. Ur é associada historicamente a qual grande região cultural?",
        "opcoes": [
          "Mesopotâmia",
          "Escandinávia",
          "Península Ibérica",
          "Vale do Indo"
        ],
        "correta": 0
      },
      {
        "pergunta": "3) Canaã, cenário central das narrativas patriarcais, corresponde aproximadamente hoje a:",
        "opcoes": [
          "Itália e Grécia",
          "Israel/Palestina e partes do Líbano e Jordânia",
          "Marrocos e Argélia",
          "Turquia central e Cáucaso"
        ],
        "correta": 1
      },
      {
        "pergunta": "4) Na tradição, o novo nome de Jacó, ligado à origem do povo, é:",
        "opcoes": [
          "Israel",
          "Judá",
          "Moisés",
          "Samuel"
        ],
        "correta": 0
      },
      {
        "pergunta": "5) A ideia religiosa que se torna base da identidade hebraica e aparece como aliança com Deus é:",
        "opcoes": [
          "Politeísmo",
          "Monoteísmo",
          "Ateísmo",
          "Culto ao imperador"
        ],
        "correta": 1
      },
      {
        "pergunta": "6) A passagem dos patriarcas para o período no Egito é tradicionalmente ligada à história de:",
        "opcoes": [
          "Sansão",
          "José (vendido pelos irmãos)",
          "Saul",
          "Salomão"
        ],
        "correta": 1
      },
      {
        "pergunta": "7) A fase do Êxodo é lembrada como saída do Egito sob a liderança de:",
        "opcoes": [
          "Davi",
          "Moisés",
          "Elias",
          "Esdras"
        ],
        "correta": 1
      },
      {
        "pergunta": "8) A celebração que recorda a libertação do Egito e marca a identidade do povo é:",
        "opcoes": [
          "Hanucá",
          "Pessach (Páscoa judaica)",
          "Purim",
          "Shavuot"
        ],
        "correta": 1
      },
      {
        "pergunta": "9) O evento do Sinai, central no Êxodo, é descrito como a entrega de:",
        "opcoes": [
          "Os Dez Mandamentos e a Lei (Torá)",
          "As Doze Tábuas romanas",
          "O Código de Hamurábi",
          "Os Evangelhos"
        ],
        "correta": 0
      },
      {
        "pergunta": "10) No período do deserto, o local móvel de culto e reunião, anterior ao Templo, era o:",
        "opcoes": [
          "Coliseu",
          "Tabernáculo (Tenda do Encontro)",
          "Zigurate",
          "Partenon"
        ],
        "correta": 1
      },
      {
        "pergunta": "11) O objeto sagrado associado à presença divina e à aliança, carregado no período do deserto, é a:",
        "opcoes": [
          "Arca da Aliança",
          "Pedra de Roseta",
          "Estela de Merneptá",
          "Tábua de argila cuneiforme"
        ],
        "correta": 0
      },
      {
        "pergunta": "12) Após a travessia, a fase inicial em Canaã (antes de reis), com conflitos e lideranças locais, é chamada de:",
        "opcoes": [
          "Era dos Patriarcas",
          "Período dos Juízes",
          "Período do Segundo Templo",
          "Período Bizantino"
        ],
        "correta": 1
      },
      {
        "pergunta": "13) No Período dos Juízes, a forma de liderança mais comum era:",
        "opcoes": [
          "Reis hereditários permanentes",
          "Governadores persas",
          "Líderes carismáticos levantados em crises",
          "Senadores eleitos por voto"
        ],
        "correta": 2
      },
      {
        "pergunta": "14) A transição para a monarquia é justificada na tradição por uma necessidade principal:",
        "opcoes": [
          "Criar comércio marítimo com a China",
          "Unificar o povo e fortalecer a defesa militar",
          "Abolir a religião e o culto",
          "Migrar para a Europa"
        ],
        "correta": 1
      },
      {
        "pergunta": "15) O primeiro rei de Israel, segundo a tradição bíblica, foi:",
        "opcoes": [
          "Saul",
          "Davi",
          "Salomão",
          "Josias"
        ],
        "correta": 0
      },
      {
        "pergunta": "16) Um adversário frequente nas narrativas do início da monarquia, associado à faixa costeira, eram os:",
        "opcoes": [
          "Persas",
          "Filisteus",
          "Romanos",
          "Macedônios"
        ],
        "correta": 1
      },
      {
        "pergunta": "17) Davi é considerado decisivo por consolidar o poder e estabelecer como capital a cidade de:",
        "opcoes": [
          "Samaria",
          "Jerusalém",
          "Tiro",
          "Babilônia"
        ],
        "correta": 1
      },
      {
        "pergunta": "18) Sob Salomão, a centralização do culto em Jerusalém é marcada pela construção do:",
        "opcoes": [
          "Primeiro Templo",
          "Segundo Templo",
          "Partenon",
          "Zigurate"
        ],
        "correta": 0
      },
      {
        "pergunta": "19) Após Salomão, a monarquia unida se divide em dois reinos. Quais são eles?",
        "opcoes": [
          "Judá (Sul) e Israel (Norte)",
          "Assíria e Babilônia",
          "Egito e Núbia",
          "Pérsia e Média"
        ],
        "correta": 0
      },
      {
        "pergunta": "20) No período dos reinos divididos, os profetas ganham destaque porque:",
        "opcoes": [
          "Defendiam apenas conquistas militares",
          "Denunciavam injustiças e cobravam fidelidade à aliança",
          "Organizavam eleições e partidos",
          "Propagavam o culto ao imperador"
        ],
        "correta": 1
      },
      {
        "pergunta": "21) O Reino de Israel (Norte) caiu primeiro, conquistado por qual império?",
        "opcoes": [
          "Assírio",
          "Romano",
          "Persa",
          "Macedônico"
        ],
        "correta": 0
      },
      {
        "pergunta": "22) Uma consequência associada à queda do Reino do Norte foi:",
        "opcoes": [
          "A destruição imediata do Segundo Templo",
          "Deportações e dispersão de parte da população",
          "A conversão de Roma ao judaísmo",
          "A fundação de Constantinopla"
        ],
        "correta": 1
      },
      {
        "pergunta": "23) O Reino de Judá (Sul) foi conquistado posteriormente por qual potência que destruiu o Primeiro Templo?",
        "opcoes": [
          "Babilônia (neobabilônios)",
          "Macedônia",
          "Cartago",
          "Egito ptolomaico"
        ],
        "correta": 0
      },
      {
        "pergunta": "24) A destruição do Primeiro Templo e o Exílio Babilônico são tradicionalmente datados de:",
        "opcoes": [
          "586 a.C.",
          "332 a.C.",
          "70 d.C.",
          "135 d.C."
        ],
        "correta": 0
      },
      {
        "pergunta": "25) No Exílio, a identidade judaica se fortalece especialmente por meio de:",
        "opcoes": [
          "Arenas e jogos públicos",
          "Lei, textos sagrados e vida comunitária",
          "Mitologia nórdica",
          "Culto aos deuses olímpicos"
        ],
        "correta": 1
      },
      {
        "pergunta": "26) Quem conquistou a Babilônia e permitiu o retorno de judeus a Judá, iniciando o domínio persa?",
        "opcoes": [
          "Ciro, o Grande",
          "Nabucodonosor II",
          "Júlio César",
          "Antíoco IV"
        ],
        "correta": 0
      },
      {
        "pergunta": "27) A reconstrução do santuário após o retorno marca o início do período do:",
        "opcoes": [
          "Segundo Templo",
          "Primeiro Templo",
          "Período dos Juízes",
          "Período Patriarcal"
        ],
        "correta": 0
      },
      {
        "pergunta": "28) No período persa e pós-exílio, qual língua se torna muito comum no cotidiano, ao lado do hebraico religioso?",
        "opcoes": [
          "Latim",
          "Aramaico",
          "Grego micênico",
          "Sânscrito"
        ],
        "correta": 1
      },
      {
        "pergunta": "29) A conquista de Alexandre, o Grande, intensifica um processo cultural sobre os judeus conhecido como:",
        "opcoes": [
          "Helenização",
          "Feudalização",
          "Industrialização",
          "Colonização atlântica"
        ],
        "correta": 0
      },
      {
        "pergunta": "30) A Revolta dos Macabeus (séc. II a.C.) foi uma reação principalmente a:",
        "opcoes": [
          "Perseguição religiosa e imposições helenísticas",
          "Expansão do cristianismo no Império Romano",
          "Invasões vikings no Mediterrâneo",
          "Conquista árabe de Jerusalém"
        ],
        "correta": 0
      },
      {
        "pergunta": "31) A festa associada à rededicação do Templo após a vitória macabeia é:",
        "opcoes": [
          "Hanucá",
          "Pessach",
          "Purim",
          "Yom Kippur"
        ],
        "correta": 0
      },
      {
        "pergunta": "32) A Grande Revolta Judaica contra Roma culminou em 70 d.C. com:",
        "opcoes": [
          "A destruição do Segundo Templo em Jerusalém",
          "A destruição do Primeiro Templo em Jerusalém",
          "A queda do Império Romano do Ocidente",
          "A assinatura da Paz de Vestfália"
        ],
        "correta": 0
      }
    ]
  }
}
